healthinsurance/HealthInsurance.py
healthinsurance/__init__.py
healthinsurance/postgres_crud.py
healthinsurance/utils.py
healthinsurance-0.1.5.dist-info/METADATA
healthinsurance-0.1.5.dist-info/WHEEL
healthinsurance-0.1.5.dist-info/top_level.txt
healthinsurance-0.1.5.dist-info/RECORD
