Metadata-Version: 1.0
Name: healthinsurance
Version: 0.1.5
Summary: Project Package
Home-page: https://www.linkedin.com/in/brunovn/
Author: bruno vinicius nonato
Author-email: brunovinicius154@gmail.com
License: MIT
Platform: UNKNOWN
